lt_hist/__init__.py
lt_hist/entrypoint.py
lt_hist/main.py
lt_hist/plot.py
lt_hist-0.1.dist-info/METADATA
lt_hist-0.1.dist-info/WHEEL
lt_hist-0.1.dist-info/entry_points.txt
lt_hist-0.1.dist-info/top_level.txt
lt_hist-0.1.dist-info/RECORD
