Metadata-Version: 2.1
Name: lt-hist
Version: 0.1
Summary: Compares the last results of Load Test
Home-page: https://github.com/ifood/lt-hist
Author: Felipe Volpone    
Author-email: felipe.volpone@ifood.com.br
License: none
Platform: UNKNOWN
Requires-Dist: boto3
Requires-Dist: matplotlib
Requires-Dist: numpy
Requires-Dist: click
